{"id":14174,"group":"94593106","joblink":true,"name":"Meister/in - Veranstaltungstechnik (Bühne/Studio)","potential":64,"skills":[{"id":60647,"skill":"Arbeitsvorbereitung","replaceable":false},{"id":61314,"skill":"Elektroinstallation","replaceable":false},{"id":61317,"skill":"Lichttechnik, Beleuchtung","replaceable":true},{"id":62252,"skill":"Kalkulation","replaceable":true},{"id":62287,"skill":"Betriebsmitteleinsatz planen","replaceable":false},{"id":65129,"skill":"Auf-, Umbau (Bühne, Film)","replaceable":false},{"id":65135,"skill":"Bühnen-, Theatertechnik","replaceable":true},{"id":65149,"skill":"Veranstaltungstechnik","replaceable":true},{"id":65361,"skill":"Aufnahmetechnik","replaceable":true},{"id":65386,"skill":"Studiotechnik","replaceable":true},{"id":65391,"skill":"Tontechnik","replaceable":true}]}