{"id":14605,"group":"34393110","joblink":true,"name":"Industriemeister/in - Rohrleitungsbau","potential":27,"skills":[{"id":60647,"skill":"Arbeitsvorbereitung","replaceable":false},{"id":60762,"skill":"Qualitätsprüfung, Qualitätssicherung","replaceable":true},{"id":61738,"skill":"Schweißtechnik","replaceable":true},{"id":61753,"skill":"Gas-, Wasserleitungsbau","replaceable":false},{"id":61763,"skill":"Rohrinstallation","replaceable":false},{"id":61769,"skill":"Versorgungstechnik","replaceable":true},{"id":61860,"skill":"Drainagearbeiten, Rohrverlegungen","replaceable":false},{"id":61879,"skill":"Rohrleitungsbau","replaceable":false},{"id":61946,"skill":"Baustelleneinrichtung","replaceable":false},{"id":62013,"skill":"Baubetrieb","replaceable":false},{"id":62287,"skill":"Betriebsmitteleinsatz planen","replaceable":false}]}