{"id":14989,"group":"81883101","joblink":true,"name":"Medical Advisor","potential":29,"skills":[{"id":61467,"skill":"Arzneimittelinformation","replaceable":true},{"id":61481,"skill":"Pharmakologie","replaceable":false},{"id":62271,"skill":"Kundenberatung, -betreuung","replaceable":false},{"id":62279,"skill":"Verkaufsförderung","replaceable":false},{"id":62331,"skill":"Präsentation","replaceable":false},{"id":62406,"skill":"Arzneimittelrecht","replaceable":true},{"id":64424,"skill":"Vortragstätigkeit","replaceable":false}]}