{"id":15633,"group":"26302131","joblink":true,"name":"Elektroniker/in - Geräte und Systeme","potential":100,"skills":[{"id":61284,"skill":"Elektromechanik","replaceable":true},{"id":61285,"skill":"Elektronik","replaceable":true},{"id":61286,"skill":"Elektrotechnik","replaceable":true},{"id":61292,"skill":"Geräteelektronik","replaceable":true},{"id":61303,"skill":"Mikroelektronik","replaceable":true},{"id":61308,"skill":"Schaltungstechnik","replaceable":true},{"id":63200,"skill":"Hardwareinstallation, Softwareinstallation","replaceable":true}]}