{"id":15682,"group":"27284100","joblink":true,"name":"Ingenieur/in - Sport","potential":45,"skills":[{"id":60647,"skill":"Arbeitsvorbereitung","replaceable":false},{"id":60663,"skill":"CAD (Computer Aided Design)-Systeme anwenden","replaceable":true},{"id":60670,"skill":"Konstruktion","replaceable":false},{"id":60676,"skill":"Projektierung","replaceable":false},{"id":60699,"skill":"Fertigungstechnik","replaceable":true},{"id":61140,"skill":"Sportgeräteherstellung","replaceable":true},{"id":62252,"skill":"Kalkulation","replaceable":true},{"id":62287,"skill":"Betriebsmitteleinsatz planen","replaceable":false},{"id":64211,"skill":"Entwicklung","replaceable":false},{"id":64968,"skill":"Sportwissenschaften","replaceable":false},{"id":66183,"skill":"Sportartikel, Sportgeräte","replaceable":true}]}