{"id":3495,"group":"28332104","joblink":true,"name":"Orthopädieschuhmacher/in","potential":85,"skills":[{"id":60423,"skill":"Zuschneiden (Textil, Bekleidung, Leder u.Ä.)","replaceable":true},{"id":60506,"skill":"Bodenmachen","replaceable":true},{"id":60511,"skill":"Fußbett anfertigen","replaceable":true},{"id":60512,"skill":"Innenschuhfertigen","replaceable":true},{"id":60513,"skill":"Leistenmachen","replaceable":true},{"id":60517,"skill":"Orthopädieschuhmachen","replaceable":false},{"id":60519,"skill":"Schäftemachen","replaceable":true},{"id":64790,"skill":"Orthesenfertigung","replaceable":true},{"id":64792,"skill":"Orthopädische Zurichtungen anbringen","replaceable":false},{"id":64794,"skill":"Prothesenfertigung (Orthopädie)","replaceable":true},{"id":66186,"skill":"Bandagen","replaceable":true},{"id":66187,"skill":"Einlagen","replaceable":true},{"id":66189,"skill":"Fußstützen/-hilfen","replaceable":true}]}