{"id":35070,"group":"33312114","joblink":true,"name":"Isolierer/in","potential":0,"skills":[{"id":61930,"skill":"Wärme- und Kältedämmungen herstellen","replaceable":false},{"id":61931,"skill":"Gebäudedämmung (Wärmeschutz) herstellen","replaceable":false},{"id":61934,"skill":"Maschinenisolieren","replaceable":false},{"id":61937,"skill":"Rohre und Behälter dämmen","replaceable":false},{"id":61938,"skill":"Schalldämmungen herstellen","replaceable":false},{"id":61941,"skill":"Ummantelungen herstellen","replaceable":false},{"id":62009,"skill":"Wand- und Deckenverkleidung","replaceable":false}]}