{"id":3537,"group":"28393103","joblink":true,"name":"Sattler- und Feintäschnermeister/in","potential":53,"skills":[{"id":60423,"skill":"Zuschneiden (Textil, Bekleidung, Leder u.Ä.)","replaceable":true},{"id":60440,"skill":"Leder - Materialkunde","replaceable":true},{"id":60442,"skill":"Lederbearbeitung, Lederverarbeitung","replaceable":true},{"id":60445,"skill":"Lederzurichtung","replaceable":true},{"id":60492,"skill":"Fahrzeugsattlerei","replaceable":false},{"id":60493,"skill":"Feinsattlerei","replaceable":false},{"id":60497,"skill":"Lederauswahl","replaceable":true},{"id":60499,"skill":"Reitsportsattlerei","replaceable":false},{"id":60502,"skill":"Taschensattlerei","replaceable":false},{"id":60647,"skill":"Arbeitsvorbereitung","replaceable":false},{"id":60714,"skill":"Maschineneinrichtung, Anlageneinrichtung","replaceable":true},{"id":60762,"skill":"Qualitätsprüfung, Qualitätssicherung","replaceable":true},{"id":62252,"skill":"Kalkulation","replaceable":true},{"id":62271,"skill":"Kundenberatung, -betreuung","replaceable":false},{"id":62287,"skill":"Betriebsmitteleinsatz planen","replaceable":false}]}