{"id":4036,"group":"32193108","joblink":true,"name":"Dachdeckermeister/in","potential":25,"skills":[{"id":60647,"skill":"Arbeitsvorbereitung","replaceable":false},{"id":61993,"skill":"Abdichten (Dach)","replaceable":false},{"id":61995,"skill":"Dachdecken","replaceable":false},{"id":61996,"skill":"Dachentwässerung","replaceable":false},{"id":62003,"skill":"Holzbauteile herstellen","replaceable":true},{"id":62008,"skill":"Unterkonstruktionen anbringen (Dach, Fassade)","replaceable":false},{"id":62252,"skill":"Kalkulation","replaceable":true},{"id":62287,"skill":"Betriebsmitteleinsatz planen","replaceable":false}]}