{"id":4246,"group":"33293101","joblink":true,"name":"Stuckateurmeister/in","potential":25,"skills":[{"id":60647,"skill":"Arbeitsvorbereitung","replaceable":false},{"id":60762,"skill":"Qualitätsprüfung, Qualitätssicherung","replaceable":true},{"id":61931,"skill":"Gebäudedämmung (Wärmeschutz) herstellen","replaceable":false},{"id":61939,"skill":"Stuckarbeiten","replaceable":false},{"id":62007,"skill":"Trockenbau","replaceable":false},{"id":62015,"skill":"Bauleitung","replaceable":false},{"id":62252,"skill":"Kalkulation","replaceable":true},{"id":62271,"skill":"Kundenberatung, -betreuung","replaceable":false}]}