{"id":5479,"group":"22103100","joblink":true,"name":"Techniker/in - Maschinentechnik (Kunststoff-/Kautschuktech.)","potential":67,"skills":[{"id":60670,"skill":"Konstruktion","replaceable":false},{"id":60690,"skill":"Betriebstechnik","replaceable":true},{"id":60699,"skill":"Fertigungstechnik","replaceable":true},{"id":60762,"skill":"Qualitätsprüfung, Qualitätssicherung","replaceable":true},{"id":61447,"skill":"Kautschuktechnologie","replaceable":false},{"id":61448,"skill":"Kautschuk-, Gummiverarbeitung","replaceable":true},{"id":61457,"skill":"Kunststofftechnik","replaceable":true},{"id":61648,"skill":"Maschinentechnik","replaceable":true},{"id":62287,"skill":"Betriebsmitteleinsatz planen","replaceable":false}]}