{"id":5528,"group":"26313103","joblink":true,"name":"Medientechniker/in (Kommunikationselektronik)","potential":88,"skills":[{"id":60762,"skill":"Qualitätsprüfung, Qualitätssicherung","replaceable":true},{"id":61285,"skill":"Elektronik","replaceable":true},{"id":61286,"skill":"Elektrotechnik","replaceable":true},{"id":61351,"skill":"Nachrichtentechnik, Kommunikationstechnik","replaceable":true},{"id":61362,"skill":"Sendeanlagen, -technik","replaceable":true},{"id":62287,"skill":"Betriebsmitteleinsatz planen","replaceable":false},{"id":65443,"skill":"Medientechnik","replaceable":true},{"id":65949,"skill":"Empfangsanlagen","replaceable":true}]}