{"id":58717,"group":"25214123","joblink":true,"name":"Ingenieur/in - Fahrzeugtechnik","potential":46,"skills":[{"id":60647,"skill":"Arbeitsvorbereitung","replaceable":false},{"id":60668,"skill":"Entwurf","replaceable":false},{"id":60670,"skill":"Konstruktion","replaceable":false},{"id":60676,"skill":"Projektierung","replaceable":false},{"id":60699,"skill":"Fertigungstechnik","replaceable":true},{"id":61214,"skill":"Fahrwerktechnik","replaceable":true},{"id":61225,"skill":"Kraftfahrzeugelektrik, Kraftfahrzeugelektronik","replaceable":true},{"id":62252,"skill":"Kalkulation","replaceable":true},{"id":62287,"skill":"Betriebsmitteleinsatz planen","replaceable":false},{"id":64211,"skill":"Entwicklung","replaceable":false},{"id":64298,"skill":"Technische Mechanik","replaceable":false},{"id":61221001,"skill":"Fahrzeugtechnik","replaceable":true},{"id":61221002,"skill":"Fahrzeugbau","replaceable":true}]}