{"id":59338,"group":"24414101","joblink":true,"name":"Stahl- und Metallbauingenieur/in","potential":8,"skills":[{"id":60647,"skill":"Arbeitsvorbereitung","replaceable":false},{"id":62013,"skill":"Baubetrieb","replaceable":false},{"id":62015,"skill":"Bauleitung","replaceable":false},{"id":62022,"skill":"Bauabnahme","replaceable":false},{"id":62025,"skill":"Baukonstruktion","replaceable":false},{"id":62028,"skill":"Bauphysik","replaceable":false},{"id":62030,"skill":"Baustatik","replaceable":false},{"id":62031,"skill":"Baustoffkunde, -technologie","replaceable":false},{"id":62039,"skill":"Konstruktiver Ingenieurbau","replaceable":false},{"id":62047,"skill":"Stahlbaukonstruktion (Planung, Überwachung)","replaceable":false},{"id":62252,"skill":"Kalkulation","replaceable":true},{"id":62287,"skill":"Betriebsmitteleinsatz planen","replaceable":false},{"id":126667,"skill":"Bauüberwachung (Objektüberwachung)","replaceable":false}]}