{"id":6631,"group":"62322100","joblink":true,"name":"Fachverkäufer/in - Nahrungsmittelhandw.(Fleischerei)","potential":54,"skills":[{"id":60989,"skill":"Fleisch- und Geflügelfleischhygiene","replaceable":false},{"id":61042,"skill":"Anrichten (Lebensmittel)","replaceable":false},{"id":62203,"skill":"Warenauszeichnung","replaceable":true},{"id":62204,"skill":"Warenpräsentation","replaceable":false},{"id":62217,"skill":"Abrechnung","replaceable":true},{"id":62269,"skill":"Kassieren","replaceable":true},{"id":62271,"skill":"Kundenberatung, -betreuung","replaceable":false},{"id":62278,"skill":"Verkauf","replaceable":false},{"id":62694,"skill":"Verpacken","replaceable":true},{"id":62696,"skill":"Warenannahme, Wareneingangskontrolle","replaceable":true},{"id":62979,"skill":"Partyservice","replaceable":false},{"id":65593,"skill":"Fleischgerichte","replaceable":true},{"id":65594,"skill":"Fleischwaren, Wurstwaren","replaceable":true}]}