{"id":8678,"group":"81464102","joblink":true,"name":"Facharzt/-채rztin - Neurologie","potential":0,"skills":[{"id":64490,"skill":"Diagnose","replaceable":false},{"id":64529,"skill":"Neurologie (채rztlich)","replaceable":false},{"id":64531,"skill":"Neuropathologie (채rztlich)","replaceable":false},{"id":64532,"skill":"Neurophysiologie","replaceable":false},{"id":64576,"skill":"Gesundheitsvorsorge (Pr채vention)","replaceable":false},{"id":64582,"skill":"Patientenbetreuung","replaceable":false},{"id":67349,"skill":"Therapie","replaceable":false}]}