{"id":90468,"group":"25242116","joblink":true,"name":"Bootsbauer/in - Technik","potential":71,"skills":[{"id":60798,"skill":"Wartung, Reparatur, Instandhaltung","replaceable":false},{"id":61252,"skill":"Bootsbau","replaceable":true},{"id":61277,"skill":"Bordelektronik (Schiff, Flugzeug, Eisenbahn, Kfz)","replaceable":true},{"id":61309,"skill":"Schiffselektrik","replaceable":true},{"id":61434,"skill":"Korrosionsschutz","replaceable":false},{"id":61636,"skill":"Antriebstechnik","replaceable":true},{"id":62769,"skill":"Schiffsausrüstung","replaceable":true}]}