{"id":90633,"group":"71214101","joblink":false,"name":"Bürgermeister/in","potential":44,"skills":[{"id":62286,"skill":"Aufbauorganisation","replaceable":false},{"id":62301,"skill":"Personalplanung","replaceable":false},{"id":62412,"skill":"Beamtenrecht","replaceable":true},{"id":62436,"skill":"Haushaltsrecht","replaceable":true},{"id":62450,"skill":"Kommunalrecht","replaceable":true},{"id":62505,"skill":"Verwaltungsrecht","replaceable":true},{"id":62560,"skill":"Haushaltswesen (öffentliche Verwaltung)","replaceable":false},{"id":64186,"skill":"Rhetorik","replaceable":false},{"id":66481,"skill":"Finanzwissenschaft, öffentliches Finanzwesen","replaceable":false}]}