{"id":958,"group":"21222116","joblink":false,"name":"Betonfertigteilbauer/in - Betonstein u. Terrazzo","potential":38,"skills":[{"id":60289,"skill":"Betonfertigteile herstellen","replaceable":true},{"id":60290,"skill":"Betonstein- und Terrazzoherstellung","replaceable":true},{"id":61982,"skill":"Terrazzolegen","replaceable":false},{"id":62053,"skill":"Betonfertigteilbau","replaceable":false},{"id":62055,"skill":"Betonmischen","replaceable":true},{"id":62056,"skill":"Betonoberflächen behandeln","replaceable":false},{"id":62059,"skill":"Eisenflechten, Bewehrungen herstellen","replaceable":false},{"id":62083,"skill":"Schalungsarbeiten","replaceable":false}]}