{"id":9908,"group":"82311100","joblink":true,"name":"Helfer/in - Friseurgewerbe","potential":22,"skills":[{"id":60747,"skill":"Waschen","replaceable":true},{"id":62192,"skill":"Regalauffüllen","replaceable":false},{"id":62269,"skill":"Kassieren","replaceable":true},{"id":62324,"skill":"Kunden-, Besucherempfang","replaceable":false},{"id":63100,"skill":"Reinigen","replaceable":false},{"id":64603,"skill":"Haarfönen","replaceable":false},{"id":64604,"skill":"Haarpflege","replaceable":false},{"id":64607,"skill":"Haarwaschen, Shampoonieren","replaceable":false},{"id":64618,"skill":"Nagelpflege, Nageldesign","replaceable":false}]}